numcurios/__init__.py
numcurios/fast_math.cp312-win_amd64.pyd
numcurios-0.1.0.dist-info/METADATA
numcurios-0.1.0.dist-info/WHEEL
numcurios-0.1.0.dist-info/top_level.txt
numcurios-0.1.0.dist-info/RECORD
