Metadata-Version: 2.4
Name: numcurios
Version: 0.1.0
Summary: Библиотека для работы с интересными числами и комбинаторикой
Author: Твоё Имя
Author-email: you@example.com
Classifier: Programming Language :: Python :: 3
Classifier: Programming Language :: C++
Classifier: Operating System :: OS Independent
Requires-Python: >=3.7
Dynamic: author
Dynamic: author-email
Dynamic: classifier
Dynamic: description
Dynamic: description-content-type
Dynamic: requires-python
Dynamic: summary
